ChangeLog
LICENSE
MANIFEST.in
README
TODO
setup.py
PyRRD.egg-info/PKG-INFO
PyRRD.egg-info/SOURCES.txt
PyRRD.egg-info/dependency_links.txt
PyRRD.egg-info/top_level.txt
docs/ACKNOWLEDGEMENTS.txt
docs/FOOTNOTES.txt
docs/HISTORY.txt
docs/PRELUDE.txt
examples/example1.png
examples/example1.py
examples/example2.png
examples/example2.py
examples/example3-large.png
examples/example3.png
examples/example3.py
examples/example4-large.png
examples/example4.png
examples/example4.py
examples/example5-10800-large.png
examples/example5-10800.png
examples/example5-259200-large.png
examples/example5-259200.png
examples/example5-43200-large.png
examples/example5-43200.png
examples/example5-86400-large.png
examples/example5-86400.png
examples/example5.py
pyrrd/__init__.py
pyrrd/backend.py
pyrrd/bindings.py
pyrrd/external.py
pyrrd/graph.py
pyrrd/mapper.py
pyrrd/meta.py
pyrrd/node.py
pyrrd/rrd.py
pyrrd/util/__init__.py
pyrrd/util/dist.py
test/__init__.py
test/test_all.py
test/test_doctests.py
test/utils.py