Metadata-Version: 1.0
Name: PyRRD
Version: 0.0.7
Summary: An Object-Oriented Python Interface for RRD
Home-page: http://code.google.com/p/pyrrd/
Author: Duncan McGreggor
Author-email: duncan@canonical.com
License: BSD
Platform: UNKNOWN
Classifier: Development Status :: 4 - Beta
Classifier: Intended Audience :: Developers
Classifier: Intended Audience :: by End-User Class :: Advanced End Users
Classifier: Intended Audience :: by End-User Class :: System Administrators
Classifier: Intended Audience :: by Industry or Sector :: Information Technology
Classifier: Programming Language :: Python
Classifier: Topic :: Database
Classifier: Topic :: Formats and Protocols :: Data Formats
Classifier: Topic :: Multimedia :: Graphics :: Presentation
Classifier: Topic :: Software Development :: Object Oriented
Classifier: Topic :: System :: Networking :: Monitoring
Classifier: Topic :: System :: Systems Administration
Classifier: License :: OSI Approved :: BSD License
